Metadata-Version: 2.1
Name: fexplorer
Version: 0.0.4
Summary: Simple file explorer made with python
Home-page: https://github.com/aysilsimgekaracan/fexplorer
Author: aysilsimgekaracan
Author-email: aysilsimge@gmail.com
License: MIT
Download-URL: https://github.com/aysilsimgekaracan/fexplorer/archive/refs/tags/v_0_0_4.tar.gz
Keywords: CLI,FILE EXPLORER,EXPLORER
Platform: UNKNOWN
Classifier: Development Status :: 2 - Pre-Alpha
Classifier: Environment :: Console
Classifier: Intended Audience :: Developers
Classifier: Topic :: Software Development :: Build Tools
Classifier: License :: OSI Approved :: MIT License
Classifier: Programming Language :: Python
Classifier: Programming Language :: Python :: 3
Classifier: Programming Language :: Python :: 3.9
Classifier: Topic :: Desktop Environment :: File Managers
License-File: LICENSE
License-File: LICENSE.txt
